README.rst
setup.py
fuss/__init__.py
fuss/benchmark.py
fuss/decorator.py
fuss.egg-info/PKG-INFO
fuss.egg-info/SOURCES.txt
fuss.egg-info/dependency_links.txt
fuss.egg-info/not-zip-safe
fuss.egg-info/pbr.json
fuss.egg-info/top_level.txt