Metadata-Version: 1.0
Name: fuss
Version: 0.2
Summary: benchmark library
Home-page: https://github.com/rohitladdha/fuss
Author: Rohit Laddha
Author-email: rohitladdh@gmail.com
License: UNKNOWN
Platform: UNKNOWN
